JDML/JDML.py
JDML/__init__.py
JDML/source/Configuration.py
JDML/source/Exception.py
JDML/source/Logger.py
JDML/source/Utils.py
JDML/source/__init__.py
JDML/source/Pipeline/Predict_Pipeline.py
JDML/source/Pipeline/Train_Pipeline.py
JDML/source/Pipeline/__init__.py
JDML/source/components/Data_Transformation.py
JDML/source/components/Data_ingestion.py
JDML/source/components/Model_Trainer.py
JDML/source/components/__init__.py
JustDataML-0.0.27.dist-info/METADATA
JustDataML-0.0.27.dist-info/WHEEL
JustDataML-0.0.27.dist-info/entry_points.txt
JustDataML-0.0.27.dist-info/top_level.txt
JustDataML-0.0.27.dist-info/RECORD
