Metadata-Version: 2.1
Name: JustDataML
Version: 0.0.27
Summary: JustDataML :Simplified Machine Learning for Everyone
Home-page: https://github.com/jaideepsinhdabhi/JustDataML
Author: Jaideepsinh Dabhi
Author-email: jadieep.dabhi7603@gmail.com
License: Apache License 2.0
Classifier: License :: OSI Approved :: Apache Software License
Classifier: Programming Language :: Python :: 3.9
Classifier: Operating System :: OS Independent
Requires-Dist: pandas
Requires-Dist: numpy
Requires-Dist: seaborn
Requires-Dist: matplotlib
Requires-Dist: scikit-learn
Requires-Dist: xgboost
Requires-Dist: setuptools
